[
null,
{"id":1,"animationId":41,"consumable":true,"damage":{"critical":false,"elementId":0,"formula":"0","type":0,"variance":20},"description":"Regeneración baja de cafeína","effects":[{"code":12,"dataId":0,"value1":0,"value2":25}],"hitType":0,"iconIndex":228,"itypeId":1,"name":"Refresco de cola","note":"","occasion":0,"price":50,"repeats":1,"scope":7,"speed":0,"successRate":100,"tpGain":0},
{"id":2,"animationId":41,"consumable":true,"damage":{"critical":false,"elementId":0,"formula":"0","type":0,"variance":20},"description":"Regeneración media de cafeína","effects":[{"code":12,"dataId":0,"value1":0,"value2":50}],"hitType":0,"iconIndex":228,"itypeId":1,"name":"Doble Espresso","note":"","occasion":0,"price":100,"repeats":1,"scope":7,"speed":0,"successRate":100,"tpGain":0},
{"id":3,"animationId":45,"consumable":true,"damage":{"critical":false,"elementId":0,"formula":"0","type":0,"variance":20},"description":"Regeneración alta de cafeína","effects":[{"code":12,"dataId":0,"value1":0,"value2":100}],"hitType":0,"iconIndex":228,"itypeId":1,"name":"Bebida Energética","note":"","occasion":0,"price":200,"repeats":1,"scope":7,"speed":0,"successRate":100,"tpGain":0},
{"id":4,"animationId":49,"consumable":true,"damage":{"critical":false,"elementId":0,"formula":"b.mhp / 2","type":0,"variance":20},"description":"Reducción baja del sueño ","effects":[{"code":11,"dataId":0,"value1":0,"value2":120}],"hitType":0,"iconIndex":176,"itypeId":1,"name":"Zumo de naranja","note":"","occasion":0,"price":300,"repeats":1,"scope":9,"speed":0,"successRate":100,"tpGain":0},
{"id":5,"animationId":49,"consumable":true,"damage":{"critical":false,"elementId":0,"formula":"b.mhp / 2","type":0,"variance":20},"description":"Reducción media del sueño ","effects":[{"code":11,"dataId":0,"value1":0,"value2":240}],"hitType":0,"iconIndex":176,"itypeId":1,"name":"Donut Glaseado","note":"","occasion":0,"price":300,"repeats":1,"scope":9,"speed":0,"successRate":100,"tpGain":0},
{"id":6,"animationId":49,"consumable":true,"damage":{"critical":false,"elementId":0,"formula":"b.mhp / 2","type":0,"variance":20},"description":"Reducción alta del sueño, con un efecto extra si se usa en combate.. ","effects":[{"code":11,"dataId":0,"value1":0,"value2":480},{"code":31,"dataId":6,"value1":3,"value2":0}],"hitType":0,"iconIndex":176,"itypeId":1,"name":"Tabascco","note":"","occasion":0,"price":300,"repeats":1,"scope":9,"speed":0,"successRate":100,"tpGain":0},
{"id":7,"animationId":0,"consumable":true,"damage":{"critical":false,"elementId":0,"formula":"0","type":0,"variance":20},"description":"Es capaz de devolver a un personaje del sueño profundo.","effects":[{"code":22,"dataId":1,"value1":1,"value2":0}],"hitType":0,"iconIndex":11,"itypeId":1,"name":"Anti-Narcolepsia","note":"","occasion":0,"price":0,"repeats":1,"scope":7,"speed":0,"successRate":100,"tpGain":0}
]